jinja2_stl/loader.py
jinja2_stl/__init__.py
jinja2_stl-0.0.1.dist-info/WHEEL
jinja2_stl-0.0.1.dist-info/metadata.json
jinja2_stl-0.0.1.dist-info/top_level.txt
jinja2_stl-0.0.1.dist-info/METADATA
jinja2_stl-0.0.1.dist-info/DESCRIPTION.rst
jinja2_stl-0.0.1.dist-info/RECORD
