Metadata-Version: 2.0
Name: jinja2-stl
Version: 0.0.1
Summary: A Filestorage template loader for Jinja2.
Home-page: https://github.com/s-m-i-t-a/jinja2_stl
Author: Jindřich Smitka
Author-email: smitka.j@gmail.com
License: MIT
Keywords: jinja2_stl
Platform: UNKNOWN
Classifier: Development Status :: 2 - Pre-Alpha
Classifier: Intended Audience :: Developers
Classifier: License :: OSI Approved :: MIT License
Classifier: Natural Language :: English
Classifier: Programming Language :: Python :: 2
Classifier: Programming Language :: Python :: 2.6
Classifier: Programming Language :: Python :: 2.7
Classifier: Programming Language :: Python :: 3
Classifier: Programming Language :: Python :: 3.3
Classifier: Programming Language :: Python :: 3.4
Requires-Dist: Jinja2 (>=2.7)
Requires-Dist: six (>=1.7.3)
